passman/__init__.py
passman/crypto.py
passman/database.py
passman/main.py
passmanage-1.0.0.dist-info/METADATA
passmanage-1.0.0.dist-info/WHEEL
passmanage-1.0.0.dist-info/entry_points.txt
passmanage-1.0.0.dist-info/top_level.txt
passmanage-1.0.0.dist-info/RECORD
