Metadata-Version: 2.4
Name: passmanage
Version: 1.0.0
Summary: A simple CLI password manager with AES encryption
Home-page: https://github.com/deepak-nkit/Password-Manager
Author: Deepak kumar saini
Author-email: ds954642@gmail.com
Classifier: Programming Language :: Python :: 3
Classifier: Operating System :: OS Independent
Requires-Python: >=3.12
Requires-Dist: cryptography
Requires-Dist: bcrypt
Dynamic: author
Dynamic: author-email
Dynamic: classifier
Dynamic: description
Dynamic: description-content-type
Dynamic: home-page
Dynamic: requires-dist
Dynamic: requires-python
Dynamic: summary
